geocom/AtmosphericCorrectionData.py
geocom/AtmosphericData.py
geocom/TCException.py
geocom/TotalStation.py
geocom/__init__.py
geocom/enums/ATRMode.py
geocom/enums/BAPDistanceMeasurementPrograms.py
geocom/enums/BAPMeasurementModes.py
geocom/enums/BAPPrismenType.py
geocom/enums/BAPReflectorTypeDefinition.py
geocom/enums/ControllerConfiguration.py
geocom/enums/Directions.py
geocom/enums/EDMMeasurementMode.py
geocom/enums/EDMMeasurementType.py
geocom/enums/FaceDef.py
geocom/enums/FineAdjustPositionMode.py
geocom/enums/LeicaReturnCode.py
geocom/enums/LockConditions.py
geocom/enums/MOTStopMode.py
geocom/enums/OnOffType.py
geocom/enums/PositionMode.py
geocom/enums/ShutDownMechanismen.py
geocom/enums/StartMode.py
geocom/enums/StopMode.py
geocom/enums/TMCInclinationSensorMeasurementProgram.py
geocom/enums/TMCMeasurementMode.py
geocom/enums/TargetTypeDefinition.py
geocom/enums/__init__.py
pygeocom-0.1.0.dist-info/licenses/LICENSE
pygeocom-0.1.0.dist-info/METADATA
pygeocom-0.1.0.dist-info/WHEEL
pygeocom-0.1.0.dist-info/top_level.txt
pygeocom-0.1.0.dist-info/RECORD
