Metadata-Version: 2.4
Name: pygeocom
Version: 0.1.0
Summary: Python library for Leica GeoCOM Total Station communication
Author-email: Stefan Printz <stefan.printz@hs-bochum.de>
License: MIT
Project-URL: Homepage, https://gitlab-ce.hs-bochum.de/fachbereich-geodaesie/pypi/pygeocom
Project-URL: Source, https://gitlab-ce.hs-bochum.de/fachbereich-geodaesie/pypi/pygeocom.git
Project-URL: Issue Tracker, https://gitlab-ce.hs-bochum.de/fachbereich-geodaesie/pypi/pygeocom/-/issues
Keywords: geodesy,surveying,coordinates,total station,leica
Classifier: Programming Language :: Python :: 3
Classifier: License :: OSI Approved :: MIT License
Classifier: Operating System :: OS Independent
License-File: LICENSE
Requires-Dist: pyserial>=3.5
Requires-Dist: pysurveytools>=0.1.0
Requires-Dist: Deprecated
Provides-Extra: test
Requires-Dist: pytest; extra == "test"
Dynamic: license-file
